sampyl/__init__.py
sampyl/app.py
sampyl/core/__init__.py
sampyl/core/element.py
sampyl/core/mixins.py
sampyl/core/shortcuts.py
sampyl/core/structures.py
sampyl-0.2.0.dist-info/DESCRIPTION.rst
sampyl-0.2.0.dist-info/METADATA
sampyl-0.2.0.dist-info/RECORD
sampyl-0.2.0.dist-info/WHEEL
sampyl-0.2.0.dist-info/metadata.json
sampyl-0.2.0.dist-info/top_level.txt
