Metadata-Version: 2.0
Name: sampyl
Version: 0.2.0
Summary: A wrapper for Selenium. This library uses custom data attributes to accelerate testing through the Selenium framework
Home-page: https://github.com/jlane9/SAMpyL
Author: John Lane
Author-email: jlane@fanthreesixty.com
License: Apache License v2.0
Download-URL: https://github.com/jlane9/SAMpyL/tarball/0.2.0
Keywords: testing selenium qa web automation
Platform: UNKNOWN
Classifier: Development Status :: 3 - Alpha
Classifier: Intended Audience :: Developers
Classifier: Programming Language :: Python :: 2.6
Classifier: Programming Language :: Python :: 2.7
Classifier: License :: OSI Approved :: MIT License
Classifier: Topic :: Software Development :: Quality Assurance
Classifier: Topic :: Software Development :: Testing
Requires-Dist: PyYAML
Requires-Dist: cssselect
Requires-Dist: lxml
